nbcorg/__init__.py
nbcorg/orgmode.py
nbcorg/templates/base.tpl
nbcorg-0.0.1.dist-info/LICENSE
nbcorg-0.0.1.dist-info/METADATA
nbcorg-0.0.1.dist-info/WHEEL
nbcorg-0.0.1.dist-info/entry_points.txt
nbcorg-0.0.1.dist-info/top_level.txt
nbcorg-0.0.1.dist-info/RECORD
