Metadata-Version: 2.1
Name: nbcorg
Version: 0.0.1
Summary: An nbconvert orgmode-exporter
Home-page: https://github.com/ahrenberg/nbcorg
Author: Lukas Ahrenberg
Author-email: lukas@ahrenberg.se
License: BSD 3-Clause License
Platform: UNKNOWN
Classifier: Programming Language :: Python :: 3
Classifier: License :: OSI Approved :: BSD License
Classifier: Operating System :: OS Independent
